bio_pype-1.0.7.dist-info/DESCRIPTION.rst
bio_pype-1.0.7.dist-info/METADATA
bio_pype-1.0.7.dist-info/RECORD
bio_pype-1.0.7.dist-info/WHEEL
bio_pype-1.0.7.dist-info/entry_points.txt
bio_pype-1.0.7.dist-info/metadata.json
bio_pype-1.0.7.dist-info/top_level.txt
pype/__config__.py
pype/__init__.py
pype/__version__.py
pype/binfmisc.py
pype/commands.py
pype/env_modules.py
pype/logger.py
pype/misc.py
pype/repos.yaml
pype/modules/__init__.py
pype/modules/pipelines.py
pype/modules/profiles.py
pype/modules/repos.py
pype/modules/snippets.py
pype/pipelines/__init__.py
pype/profiles/__init__.py
pype/queues/__init__.py
pype/snippets/__init__.py
pype/utils/__init__.py
pype/utils/arguments.py
pype/utils/pipeline.py
pype/utils/profiles.py
pype/utils/queues.py
